LICENSE
MANIFEST.in
README.md
setup.cfg
setup.py
tests/__init__.py
tests/conftest.py
tests/integration/__init__.py
tests/integration/test_TruStar.py
tests/unit/__init__.py
tests/unit/test_enclaves.py
tests/unit/test_indicators.py
tests/unit/test_phishing.py
tests/unit/test_reports.py
tests/unit/test_trustar.py
trustar/__init__.py
trustar/api_client.py
trustar/config.py
trustar/indicator_client.py
trustar/log.py
trustar/phishing_triage_client.py
trustar/report_client.py
trustar/tag_client.py
trustar/trustar.py
trustar/utils.py
trustar/version.py
trustar.egg-info/PKG-INFO
trustar.egg-info/SOURCES.txt
trustar.egg-info/dependency_links.txt
trustar.egg-info/requires.txt
trustar.egg-info/top_level.txt
trustar/examples/basic_usage.py
trustar/examples/bulk_upload.py
trustar/examples/create_indicators_csv.py
trustar/examples/delete_reports.py
trustar/examples/indicator_bulk_export.py
trustar/examples/ingest_csv.py
trustar/examples/ingest_fireeye_alerts.py
trustar/examples/simple_ingest_csv/simple_ingest_csv.py
trustar/models/__init__.py
trustar/models/base.py
trustar/models/cursor_page.py
trustar/models/enclave.py
trustar/models/enum.py
trustar/models/indicator.py
trustar/models/indicator_summary.py
trustar/models/intelligence_source.py
trustar/models/numbered_page.py
trustar/models/page.py
trustar/models/phishing_submission.py
trustar/models/redacted_report.py
trustar/models/report.py
trustar/models/request_quota.py
trustar/models/tag.py