Metadata-Version: 2.1
Name: trustar
Version: 0.4.1
Summary: Python SDK for the TruSTAR REST API
Home-page: https://github.com/trustar/trustar-python
Download-URL: https://github.com/trustar/trustar-python/tarball/0.4.1
Author: TruSTAR Technology, Inc.
Author-email: support@trustar.co
License: MIT
License-File: LICENSE
Requires-Dist: json_log_formatter
Requires-Dist: python-dateutil
Requires-Dist: pytz
Requires-Dist: requests
Requires-Dist: configparser
Requires-Dist: tzlocal
Requires-Dist: PyYAML
